.hgignore
.hgtags
.travis.yml
CHANGES.md
COPYING
COPYING.LESSER
appveyor.yml
requirements.txt
setup.py
test-requirements.txt
tox.ini
zetup.ini
morepy/__init__.py
morepy/magic.py
morepy/zetup_config.py
morepy.egg-info/PKG-INFO
morepy.egg-info/SOURCES.txt
morepy.egg-info/dependency_links.txt
morepy.egg-info/requires.txt
morepy.egg-info/top_level.txt
test/ipython.robot
test/load_and_run_magic.robot